mmit/__init__.py
mmit/base/__init__.py
mmit/base/activations.py
mmit/base/extra.py
mmit/base/mismatch.py
mmit/base/modules.py
mmit/base/norms.py
mmit/base/upsamplers.py
mmit/decoders/__init__.py
mmit/decoders/basedecoder.py
mmit/decoders/deeplabv3/__init__.py
mmit/decoders/deeplabv3/aspp.py
mmit/decoders/deeplabv3/model.py
mmit/decoders/deeplabv3/parts.py
mmit/decoders/deeplabv3plus/__init__.py
mmit/decoders/deeplabv3plus/aspp.py
mmit/decoders/deeplabv3plus/model.py
mmit/decoders/deeplabv3plus/parts.py
mmit/decoders/fpn/__init__.py
mmit/decoders/fpn/model.py
mmit/decoders/fpn/parts.py
mmit/decoders/linknet/__init__.py
mmit/decoders/linknet/model.py
mmit/decoders/linknet/parts.py
mmit/decoders/pan/__init__.py
mmit/decoders/pan/fpa.py
mmit/decoders/pan/gau.py
mmit/decoders/pan/model.py
mmit/decoders/pspnet/__init__.py
mmit/decoders/pspnet/model.py
mmit/decoders/pspnet/parts.py
mmit/decoders/unet/__init__.py
mmit/decoders/unet/model.py
mmit/decoders/unet/parts.py
mmit/decoders/unetplusplus/__init__.py
mmit/decoders/unetplusplus/model.py
mmit/decoders/utils/__init__.py
mmit/decoders/utils/resize.py
mmit/decoders/utils/resizing_warning.py
mmit/encoders/__init__.py
mmit/encoders/basencoder.py
mmit/encoders/timm/__init__.py
mmit/encoders/timm/model.py
mmit/factory/__init__.py
mmit/factory/components.py
mmit/factory/factory.py
mmit/factory/registry.py
mmit/heads/__init__.py
mmit/heads/classification.py
mmit/heads/segmentation.py
mmit/models/__init__.py
mmit/models/model.py
mmit-0.6.0.dist-info/LICENSE
mmit-0.6.0.dist-info/METADATA
mmit-0.6.0.dist-info/WHEEL
mmit-0.6.0.dist-info/top_level.txt
mmit-0.6.0.dist-info/RECORD
