Metadata-Version: 2.1
Name: mmit
Version: 0.6.0
Summary: A Python package for computer vision experiments and research.
Author-email: Andrea Boscolo Camiletto <abcamiletto@gmail.com>
Project-URL: Homepage, https://github.com/abcamiletto/mmit
Project-URL: Repository, https://github.com/abcamiletto/mmit
Requires-Python: >=3.8
License-File: LICENSE
Requires-Dist: timm >=0.9.0
Requires-Dist: torch >=1.10
Provides-Extra: dev
Requires-Dist: black ; extra == 'dev'
Requires-Dist: bumpver ; extra == 'dev'
Requires-Dist: pytest ; extra == 'dev'
Requires-Dist: pytest-cov ; extra == 'dev'
Requires-Dist: pytest-lazy-fixture ; extra == 'dev'
Requires-Dist: pre-commit ; extra == 'dev'
Provides-Extra: docs
Requires-Dist: sphinx ==6.2.1 ; extra == 'docs'
Requires-Dist: sphinx-rtd-theme ==1.2.0 ; extra == 'docs'
Requires-Dist: sphinx-copybutton ==0.5.2 ; extra == 'docs'
Requires-Dist: sphinx-autodoc-typehints ==1.23.0 ; extra == 'docs'
Requires-Dist: myst-parser ==1.0.0 ; extra == 'docs'
Requires-Dist: sphinx-autobuild ; extra == 'docs'
